materia/.gitignore
materia/spectra/ASTMG173.csv
materia/spectra/CIE_A.csv
materia/spectra/CIE_CMF_X.csv
materia/spectra/CIE_CMF_Y.csv
materia/spectra/CIE_CMF_Z.csv
materia/spectra/CIE_D65.csv
materia/spectra/CIE_F.csv
materia/spectra/CIE_S0.csv
materia/spectra/CIE_S1.csv
materia/spectra/CIE_S2.csv
materia/spectra/CIE_TCS.csv
materia/spectra/__init__.py
materia/spectra/spectra.py
materia_spectra-1.1.0.dist-info/LICENSE
materia_spectra-1.1.0.dist-info/WHEEL
materia_spectra-1.1.0.dist-info/METADATA
materia_spectra-1.1.0.dist-info/RECORD
