Metadata-Version: 2.1
Name: materia-spectra
Version: 1.1.0
Summary: Toolkit to analyze spectra.
Home-page: https://github.com/kijanac/materia-spectra
License: MIT
Author: Ki-Jana Carter
Author-email: kijana@mit.edu
Requires-Python: >=3.9,<3.11
Classifier: License :: OSI Approved :: MIT License
Classifier: Programming Language :: Python :: 3
Classifier: Programming Language :: Python :: 3.10
Classifier: Programming Language :: Python :: 3.9
Requires-Dist: matplotlib (>=3.5.1,<4.0.0)
Requires-Dist: numpy (>=1.21.1,<2.0.0)
Requires-Dist: scipy (>=1.7.3,<2.0.0)
Requires-Dist: unyt (>=2.8.0,<3.0.0)
Project-URL: Repository, https://github.com/kijanac/materia-spectra
